{
    "scene_descriptions": [
        "There’s a sense of **fear**, enhanced by  tones.",
        "The use of **gray** gives a **numb** feeling.",
        "With a lot of **yellow**, the mood becomes **spirited**.",
        "The choice of **green** likely connects to a **tranquil** tone.",
        "This **pink** color brings out something **innocent**."
    ],
    "object_descriptions": {
        "2087_tree": [
            "Its presence brings a sense of **growth**.",
            "Its coloring feels **numb** and organic.",
            "The medium size tree feels **balanced**.",
            "In the bottom center, it roots the scene with a **rooted and central** sense."
        ],
        "5773_house": [
            "The house may symbolize **memory**.",
            "The house is depicted in a **affectionate** manner.",
            "This medium-sized house gives a **balanced** presence.",
            "A house drawn at the top-left projects **elevated and nostalgic** and **superior**."
        ],
        "7500_house": [
            "This home-like shape evokes a sense of **safety**.",
            "Its colors create a **innocent** impression of familiarity.",
            "This medium-sized house gives a **settled** presence.",
            "A house drawn at the top-left projects **elevated and nostalgic** and **superior**."
        ]
    },
    "expression_descriptions": {
        "expr_888289d2": [
            "This smile radiates something **delighted**."
        ],
        "expr_37f25254": [
            "A happy expression shines with a **smiling** feeling."
        ],
        "expr_883b26cd": [
            "This smile radiates something **delighted**."
        ]
    },
    "full_paragraph": "Main Emotion: fear There’s a sense of fear, enhanced by  tones.\nThe use of gray gives a numb feeling. With a lot of yellow, the mood becomes spirited.\nThe choice of green likely connects to a tranquil tone.\nThis pink color brings out something innocent. Its presence brings a sense of growth.\nIts coloring feels numb and organic. The medium size tree feels balanced.\nIn the bottom center, it roots the scene with a rooted and central sense.\nThe house may symbolize memory. The house is depicted in a affectionate manner.\nThis medium-sized house gives a balanced presence.\nA house drawn at the top-left projects elevated and nostalgic and superior.\nThis home-like shape evokes a sense of safety.\nIts colors create a innocent impression of familiarity.\nThis medium-sized house gives a settled presence.\nA house drawn at the top-left projects elevated and nostalgic and superior.\nThis smile radiates something delighted. A happy expression shines with a smiling feeling.\nThis smile radiates something delighted."
}